readableidgen/__init__.py
readableidgen/util.py
readableidgen/corpus/adjectives.txt
readableidgen/corpus/nouns.txt
readableidgen-0.1.4.dist-info/LICENSE
readableidgen-0.1.4.dist-info/METADATA
readableidgen-0.1.4.dist-info/WHEEL
readableidgen-0.1.4.dist-info/top_level.txt
readableidgen-0.1.4.dist-info/RECORD
