Metadata-Version: 2.1
Name: readableidgen
Version: 0.1.4
Summary: Human-readable phrase id generator
Home-page: https://github.com/StefanHeng/Readable-Id-Generator
Author: Stefan/Yuzhao Heng
Author-email: stefan.hg@outlook.com
License: MIT
Download-URL: https://github.com/StefanHeng/Readable-Id-Generator/archive/refs/tags/v0.1.tar.gz
Keywords: python,id,generator,nlp
Platform: UNKNOWN
Classifier: Development Status :: 2 - Pre-Alpha
Classifier: Environment :: MacOS X
Classifier: Intended Audience :: End Users/Desktop
Classifier: Intended Audience :: Science/Research
Classifier: Operating System :: MacOS
Classifier: Programming Language :: Python :: 3
Classifier: Topic :: Utilities
License-File: LICENSE
Requires-Dist: colorama
Requires-Dist: numpy
